intent_markup/intent_markup.py
intent_markup/intent_markup_parser.py
intent_markup-0.10.0.dist-info/entry_points.txt
intent_markup-0.10.0.dist-info/WHEEL
intent_markup-0.10.0.dist-info/METADATA
intent_markup-0.10.0.dist-info/RECORD
