Metadata-Version: 2.1
Name: intent-markup
Version: 0.10.0
Summary: Intent Markup library for digital assistant of AIOS.
Author: Leftshift One
Author-email: contact@leftshift.one
Requires-Python: >=3.5,<4.0
Classifier: Programming Language :: Python :: 3
Classifier: Programming Language :: Python :: 3.5
Classifier: Programming Language :: Python :: 3.6
Classifier: Programming Language :: Python :: 3.7
Classifier: Programming Language :: Python :: 3.8
